tonapi/__init__.py
tonapi/main.py
AioTonApi-0.1.1.dist-info/LICENSE
AioTonApi-0.1.1.dist-info/METADATA
AioTonApi-0.1.1.dist-info/WHEEL
AioTonApi-0.1.1.dist-info/top_level.txt
AioTonApi-0.1.1.dist-info/RECORD
