Metadata-Version: 2.2
Name: AioTonApi
Version: 0.1.1
Home-page: https://github.com/vladdintov/TonAPI/
Author: vladdintov
Author-email: Your Name <you@example.com>
Requires-Python: >=3.7
License-File: LICENSE
Requires-Dist: aiogram>=3.17.0
Requires-Dist: aiohttp>=3.11.11
Dynamic: author
Dynamic: home-page
Dynamic: requires-python
